{
  "hash": "bcedebb6",
  "configHash": "f07823be",
  "lockfileHash": "e47b0fe0",
  "browserHash": "dceae4d1",
  "optimized": {
    "vue": {
      "src": "../../../../node_modules/vue/dist/vue.runtime.esm-bundler.js",
      "file": "vue.js",
      "fileHash": "1fdc5d33",
      "needsInterop": false
    },
    "vitepress > @vue/devtools-api": {
      "src": "../../../../node_modules/@vue/devtools-api/dist/index.js",
      "file": "vitepress___@vue_devtools-api.js",
      "fileHash": "0b925e84",
      "needsInterop": false
    },
    "vitepress > @vueuse/core": {
      "src": "../../../../node_modules/@vueuse/core/index.mjs",
      "file": "vitepress___@vueuse_core.js",
      "fileHash": "0e64ce14",
      "needsInterop": false
    },
    "@theme/index": {
      "src": "../../../../node_modules/vitepress/dist/client/theme-default/index.js",
      "file": "@theme_index.js",
      "fileHash": "84d819f3",
      "needsInterop": false
    }
  },
  "chunks": {
    "chunk-P2XGSYO7": {
      "file": "chunk-P2XGSYO7.js"
    },
    "chunk-HVR2FF6M": {
      "file": "chunk-HVR2FF6M.js"
    }
  }
}